{
    "version": "0.2",
    "ignorePaths": [],
    "dictionaryDefinitions": [],
    "dictionaries": [],
    "words": [
        "ACPI",
        "aranges",
        "canonicality",
        "clippy",
        "demangle",
        "demangled",
        "Devenv",
        "direnv",
        "fract",
        "framebuffers",
        "gimli",
        "kenter",
        "limine",
        "loclists",
        "memblock",
        "memmap",
        "Mmio",
        "newtype",
        "noto",
        "OVMF",
        "PDPT",
        "repr",
        "riscv",
        "rnglists",
        "rodata",
        "RSDP",
        "rustc",
        "symbolicate",
        "Symbolicates",
        "symbolication",
        "Symbolicator",
        "SYMTAB",
        "Udata",
        "uninit",
        "unmapping",
        "Unmaps",
        "vaddr",
        "Virt"
    ],
    "ignoreWords": [],
    "import": []
}
